NEURAL_py_EEG/IBI_features.py
NEURAL_py_EEG/NEURAL_parameters.py
NEURAL_py_EEG/__init__.py
NEURAL_py_EEG/amplitude_features.py
NEURAL_py_EEG/connectivity_features.py
NEURAL_py_EEG/demos.py
NEURAL_py_EEG/fd_features.py
NEURAL_py_EEG/generate_all_features.py
NEURAL_py_EEG/mfiltfilt.py
NEURAL_py_EEG/preprocessing_EEG.py
NEURAL_py_EEG/rEEG.py
NEURAL_py_EEG/spectral_features.py
NEURAL_py_EEG/utils.py
NEURAL_py_EEG-0.1.4.dist-info/LICENSE.md
NEURAL_py_EEG-0.1.4.dist-info/METADATA
NEURAL_py_EEG-0.1.4.dist-info/WHEEL
NEURAL_py_EEG-0.1.4.dist-info/top_level.txt
NEURAL_py_EEG-0.1.4.dist-info/RECORD
