Metadata-Version: 2.1
Name: NEURAL-py-EEG
Version: 0.1.4
Summary: A Neonatal EEG Pre-Processing and Feature Set in python
Home-page: https://github.com/BrianMur92/NEURAL_py_EEG_feature_set
Author: Brian Murphy
Author-email: Brian.M.Murphy@umail.ucc.ie
Project-URL: Bug Tracker, https://github.com/BrianMur92/NEURAL_py_EEG_feature_set/issues
Classifier: Programming Language :: Python :: 3
Classifier: License :: OSI Approved :: BSD License
Classifier: Operating System :: OS Independent
Requires-Python: >=3.6
License-File: LICENSE.md
